flake8p/__init__.py
flake8p/__main__.py
flake8p/hook.py
flake8p/meta.py
flake8_pyproject-1.2.2.dist-info/entry_points.txt
flake8_pyproject-1.2.2.dist-info/license.txt
flake8_pyproject-1.2.2.dist-info/WHEEL
flake8_pyproject-1.2.2.dist-info/METADATA
flake8_pyproject-1.2.2.dist-info/RECORD
