Metadata-Version: 2.1
Name: Flake8-pyproject
Version: 1.2.2
Summary: Flake8 plug-in loading the configuration from pyproject.toml
Keywords: Flake8,pyproject.toml
Author: John Hennig
Requires-Python: >= 3.6
Classifier: Development Status :: 5 - Production/Stable
Classifier: Programming Language :: Python
Classifier: Topic :: Software Development :: Quality Assurance
Classifier: Intended Audience :: Developers
Classifier: Environment :: Console
Classifier: Framework :: Flake8
Classifier: License :: OSI Approved :: MIT License
Requires-Dist: Flake8 >= 5
Requires-Dist: TOMLi; python_version < "3.11"
Requires-Dist: TOMLi < 2; python_version < "3.7"
Requires-Dist: pyTest ; extra == "dev"
Requires-Dist: pyTest-cov ; extra == "dev"
Project-URL: Source, https://github.com/john-hen/Flake8-pyproject
Provides-Extra: dev
